egobox/__init__.py
egobox/egobox.cpython-312-powerpc64le-linux-gnu.so
egobox/egobox.pyi
egobox/examples/g24.py
egobox/examples/g24_fcstr.py
egobox/examples/iooss_function.py
egobox/examples/kriging.py
egobox/examples/rastrigin.py
egobox/examples/rosenbrock_trego_viz.py
egobox/examples/sampling.py
egobox/tests/test_egor.py
egobox/tests/test_gpmix.py
egobox/tests/test_mixintegor.py
egobox/tests/test_sampling.py
egobox/tests/test_sgpmix.py
egobox/tests/test_utils.py
egobox-0.35.1.dist-info/METADATA
egobox-0.35.1.dist-info/WHEEL
egobox-0.35.1.dist-info/RECORD
